pycontroldae/__init__.py
pycontroldae/requirements.txt
pycontroldae/blocks/__init__.py
pycontroldae/blocks/basic.py
pycontroldae/blocks/linear.py
pycontroldae/blocks/sources.py
pycontroldae/core/__init__.py
pycontroldae/core/backend.py
pycontroldae/core/composite.py
pycontroldae/core/events.py
pycontroldae/core/expression_parser.py
pycontroldae/core/module.py
pycontroldae/core/port.py
pycontroldae/core/result.py
pycontroldae/core/simulator.py
pycontroldae/core/system.py
pycontroldae/examples/__init__.py
pycontroldae/examples/simple_rc.py
pycontroldae-0.2.2.dist-info/licenses/LICENSE
pycontroldae-0.2.2.dist-info/METADATA
pycontroldae-0.2.2.dist-info/WHEEL
pycontroldae-0.2.2.dist-info/top_level.txt
pycontroldae-0.2.2.dist-info/RECORD
