Metadata-Version: 2.4
Name: pycontroldae
Version: 0.2.2
Summary: A powerful Python library for building, simulating, and analyzing control systems with Julia backend
Author: PyControlDAE Contributors
Maintainer: PyControlDAE Contributors
License: MIT
Project-URL: Homepage, https://github.com/pronoobe/pycontroldae
Project-URL: Documentation, https://github.com/pronoobe/pycontroldae#readme
Project-URL: Repository, https://github.com/pronoobe/pycontroldae
Project-URL: Bug Tracker, https://github.com/pronoobe/pycontroldae/issues
Keywords: control-systems,simulation,modeling,differential-equations,julia,pid-controller,state-space,dae,ode
Classifier: Development Status :: 3 - Alpha
Classifier: Intended Audience :: Science/Research
Classifier: Intended Audience :: Developers
Classifier: License :: OSI Approved :: MIT License
Classifier: Operating System :: OS Independent
Classifier: Programming Language :: Python :: 3
Classifier: Programming Language :: Python :: 3.8
Classifier: Programming Language :: Python :: 3.9
Classifier: Programming Language :: Python :: 3.10
Classifier: Programming Language :: Python :: 3.11
Classifier: Programming Language :: Python :: 3.12
Classifier: Topic :: Scientific/Engineering
Classifier: Topic :: Scientific/Engineering :: Mathematics
Classifier: Topic :: Software Development :: Libraries :: Python Modules
Requires-Python: >=3.8
License-File: LICENSE
Requires-Dist: juliacall>=0.9.0
Requires-Dist: numpy>=1.20.0
Requires-Dist: pandas>=1.3.0
Provides-Extra: dev
Requires-Dist: pytest>=7.0; extra == "dev"
Requires-Dist: pytest-cov>=4.0; extra == "dev"
Requires-Dist: black>=23.0; extra == "dev"
Requires-Dist: flake8>=6.0; extra == "dev"
Requires-Dist: mypy>=1.0; extra == "dev"
Provides-Extra: docs
Requires-Dist: sphinx>=5.0; extra == "docs"
Requires-Dist: sphinx-rtd-theme>=1.0; extra == "docs"
Provides-Extra: visualization
Requires-Dist: matplotlib>=3.5.0; extra == "visualization"
Dynamic: license-file
